src/__init__.py
src/__main__.py
src/config.py
src/configuration.py
src/dataset.py
src/function.py
src/register.py
src/test.py
src/assets/config_template.py
src/assets/function_template.py
src/assets/pandioml-1.0.2-py3-none-any.whl
src/assets/pandioml-1.0.5-py3-none-any.whl
src/assets/pandioml_requirements.txt
src/assets/requirements_template.txt
src/assets/runner.py
src/assets/wrapper.py
src/assets/dataset/config_template.py
src/assets/dataset/csv_template.py
src/assets/dataset/mysql_template.py
src/assets/dataset/people_template.py
src/assets/dataset/stream_template.py
src/assets/dataset/trino_template.py
src/assets/dataset/wrapper.py
tests/__init__.py
tests/test_pandiocli.py
pandiocli-1.0.17.dist-info/LICENSE
pandiocli-1.0.17.dist-info/METADATA
pandiocli-1.0.17.dist-info/WHEEL
pandiocli-1.0.17.dist-info/entry_points.txt
pandiocli-1.0.17.dist-info/top_level.txt
pandiocli-1.0.17.dist-info/RECORD
