Metadata-Version: 2.1
Name: pandiocli
Version: 1.0.17
Summary: CLI to control Pandio's machine learning service.
Home-page: https://github.com/pandio-com/pandiocli
Author: Joshua Odmark
Author-email: josh@pandio.com
License: UNKNOWN
Platform: UNKNOWN
Classifier: Programming Language :: Python :: 3
Classifier: Operating System :: OS Independent
Classifier: Topic :: Documentation
Classifier: Development Status :: 5 - Production/Stable
Classifier: Intended Audience :: Developers
License-File: LICENSE
Requires-Dist: goodconf (==1.0.0)
Requires-Dist: requests (==2.25.1)
Requires-Dist: pandioml (==1.0.13)
Requires-Dist: pyinstaller (==4.3)
Requires-Dist: Faker (==8.1.1)
Requires-Dist: appdirs (==1.4.4)
Requires-Dist: requests-toolbelt (==0.9.1)
Requires-Dist: docker (==5.0.0)
